c5/__init__.py
c5/constants.py
c5/contract.py
c5/control.py
c5/database.py
c5/macros.py
c5/main.py
c5/operators.py
c5/rules.py
c5-0.1.0.dist-info/METADATA
c5-0.1.0.dist-info/WHEEL
c5-0.1.0.dist-info/RECORD
